{
    "version": 1.0,
    "author": "Blind Author",
    "description": "Get the current time using an RTC sensor",
    "config": {
        "gnd_pin": "GND.2",
        "vcc_pin": "5V"
    },
    "parts": [
        {
            "id": "arduino uno1",
            "type": "wokwi-arduino-uno",
            "top": 0,
            "left": 20
        },
        {
            "id": "ds1307 real time clock module1307",
            "type": "wokwi-ds1307",
            "top": 250,
            "left": 220,
            "attrs": {
                "initTime": "2024-11-24T04:48:00"
            }
        }
    ],
    "connections": [
        [
            "arduino uno1:GND.2",
            "ds1307 real time clock module1307:GND",
            "black",
            [
                "v20",
                "*",
                "v0"
            ]
        ],
        [
            "arduino uno1:5V",
            "ds1307 real time clock module1307:5V",
            "red",
            [
                "v0"
            ]
        ],
        [
            "arduino uno1:A4",
            "ds1307 real time clock module1307:SDA",
            "green",
            [
                "v16",
                "h0",
                "*",
                "h-34"
            ]
        ],
        [
            "arduino uno1:A5",
            "ds1307 real time clock module1307:SCL",
            "orange",
            [
                "v20",
                "*",
                "h-30"
            ]
        ]
    ]
}