{
    "version": 1.0,
    "author": "Blind Author",
    "description": "Read value of MPU6050",
    "config": {
        "scl_pin": "A5",
        "sda_pin": "A4",
        "gnd_pin": "GND.3"
    },
    "parts": [
        {
            "type": "wokwi-breadboard",
            "id": "breadboard1",
            "top": 208.2,
            "left": -189.2,
            "attrs": {}
        },
        {
            "type": "wokwi-arduino-uno",
            "id": "arduino uno1",
            "top": -9,
            "left": -19.8,
            "attrs": {}
        },
        {
            "type": "wokwi-mpu6050",
            "id": "mpu6050 6-axis accel & gyro sensor1",
            "top": 291.82,
            "left": 117.52,
            "attrs": {}
        }
    ],
    "connections": [
        [
            "mpu6050 6-axis accel & gyro sensor1:INT",
            "breadboard1:31t.e",
            "",
            [
                "$bb"
            ]
        ],
        [
            "mpu6050 6-axis accel & gyro sensor1:AD0",
            "breadboard1:32t.e",
            "",
            [
                "$bb"
            ]
        ],
        [
            "mpu6050 6-axis accel & gyro sensor1:XCL",
            "breadboard1:33t.e",
            "",
            [
                "$bb"
            ]
        ],
        [
            "mpu6050 6-axis accel & gyro sensor1:XDA",
            "breadboard1:34t.e",
            "",
            [
                "$bb"
            ]
        ],
        [
            "mpu6050 6-axis accel & gyro sensor1:SDA",
            "breadboard1:35t.e",
            "",
            [
                "$bb"
            ]
        ],
        [
            "mpu6050 6-axis accel & gyro sensor1:SCL",
            "breadboard1:36t.e",
            "",
            [
                "$bb"
            ]
        ],
        [
            "mpu6050 6-axis accel & gyro sensor1:GND",
            "breadboard1:37t.e",
            "",
            [
                "$bb"
            ]
        ],
        [
            "mpu6050 6-axis accel & gyro sensor1:VCC",
            "breadboard1:38t.e",
            "",
            [
                "$bb"
            ]
        ],
        [
            "breadboard1:38t.c",
            "breadboard1:tp.30",
            "green",
            [
                "v0"
            ]
        ],
        [
            "arduino uno1:3.3V",
            "breadboard1:tp.25",
            "green",
            [
                "v0"
            ]
        ],
        [
            "breadboard1:37t.d",
            "breadboard1:tn.29",
            "green",
            [
                "v0"
            ]
        ],
        [
            "breadboard1:36t.d",
            "arduino uno1:A5",
            "green",
            [
                "v0"
            ]
        ],
        [
            "breadboard1:35t.d",
            "arduino uno1:A4",
            "green",
            [
                "v0"
            ]
        ],
        [
            "arduino uno1:GND.3",
            "breadboard1:tn.27",
            "black",
            [
                "v0"
            ]
        ]
    ],
    "dependencies": {}
}