{"version": 1.0, "author": "Blind Author", "description": "Read value of photoresistor", "config": {"photoresistor_pin": "A2", "lux": "500", "gnd_pin": "GND.2"}, "parts": [{"type": "wokwi-arduino-uno", "id": "arduino uno1", "top": 87, "left": 47.4, "attrs": {}}, {"type": "wokwi-photoresistor-sensor", "id": "photoresistor1", "top": 3.2, "left": 96.8, "attrs": {"lux": "500"}}], "connections": [["photoresistor1:VCC", "arduino uno1:5V", "red", ["h76.8", "v115.2"]], ["photoresistor1:GND", "arduino uno1:GND.2", "black", ["h0"]], ["photoresistor1:AO", "arduino uno1:A2", "green", ["h0"]]], "dependencies": {}}